simpledf
