Metadata-Version: 1.0
Name: simpledf
Version: 0.11
Summary: A simple, easier-to-use implementation of dataframes.
Home-page: http://github.com/ankur-gupta/simpledf
Author: Ankur Gupta, Bryson Hagerman
Author-email: ankur@perfectlyrandom.org, brysonova@gmail.com
License: MIT
Keywords: dataframes pandas groupby apply custom function
Platform: UNKNOWN
